{
    "1": {
        "productID": "1",
        "productName": "Laptop",
        "productBrand": "Dell",
        "Category": "Electronics",
        "Price (INR)": 56000,
        "Product Description": "Powerful laptop with Intel Core i5 processor, 8GB RAM, and 512GB SSD. Perfect for work and entertainment.",
        "Product Image": "https://images.unsplash.com/photo-1543297088-974cee3f2156?crop=entropy&cs=tinysrgb&fit=max&fm=jpg&ixid=M3w1NjQ3NjZ8MHwxfHJhbmRvbXx8fHx8fHx8fDE3MDc2NTI4NDJ8&ixlib=rb-4.0.3&q=80&w=1080"
    },
    "2": {
        "productID": "2",
        "productName": "Smartphone",
        "productBrand": "Samsung",
        "Category": "Electronics",
        "Price (INR)": 70000,
        "Product Description": "Latest smartphone with high-resolution display, powerful camera, and long-lasting battery life.",
        "Product Image": "https://images.unsplash.com/photo-1519598944665-ff9c7f8abafe?crop=entropy&cs=tinysrgb&fit=max&fm=jpg&ixid=M3w1NjQ3NjZ8MHwxfHJhbmRvbXx8fHx8fHx8fDE3MDc2NTI4NDN8&ixlib=rb-4.0.3&q=80&w=1080"
    },
    "3": {
        "productID": "3",
        "productName": "Headphones",
        "productBrand": "Sony",
        "Category": "Electronics",
        "Price (INR)": 10500,
        "Product Description": "Premium headphones with noise-canceling technology, delivering immersive audio experience.",
        "Product Image": "https://images.unsplash.com/photo-1630713815198-17ff8a8a7103?crop=entropy&cs=tinysrgb&fit=max&fm=jpg&ixid=M3w1NjQ3NjZ8MHwxfHJhbmRvbXx8fHx8fHx8fDE3MDc2NTI4NDR8&ixlib=rb-4.0.3&q=80&w=1080"
    },
    "4": {
        "productID": "4",
        "productName": "T-shirt",
        "productBrand": "Nike",
        "Category": "Clothing",
        "Price (INR)": 1750,
        "Product Description": "Comfortable cotton t-shirt with iconic Nike logo.",
        "Product Image": "https://images.unsplash.com/photo-1566207274740-0f8cf6b7d5a5?crop=entropy&cs=tinysrgb&fit=max&fm=jpg&ixid=M3w1NjQ3NjZ8MHwxfHJhbmRvbXx8fHx8fHx8fDE3MDc2NTI4NDV8&ixlib=rb-4.0.3&q=80&w=1080"
    },
    "5": {
        "productID": "5",
        "productName": "Jeans",
        "productBrand": "Levi's",
        "Category": "Clothing",
        "Price (INR)": 3500,
        "Product Description": "Classic denim jeans from Levi's, offering style and durability.",
        "Product Image": "https://images.unsplash.com/photo-1518026620598-11e8ca5662c3?crop=entropy&cs=tinysrgb&fit=max&fm=jpg&ixid=M3w1NjQ3NjZ8MHwxfHJhbmRvbXx8fHx8fHx8fDE3MDc2NTI4NDV8&ixlib=rb-4.0.3&q=80&w=1080"
    },
    "6": {
        "productID": "6",
        "productName": "Sneakers",
        "productBrand": "Adidas",
        "Category": "Clothing",
        "Price (INR)": 5600,
        "Product Description": "Stylish sneakers with Adidas' signature design and comfortable cushioning.",
        "Product Image": "https://images.unsplash.com/photo-1642769512179-0a0a1edce4af?crop=entropy&cs=tinysrgb&fit=max&fm=jpg&ixid=M3w1NjQ3NjZ8MHwxfHJhbmRvbXx8fHx8fHx8fDE3MDc2NTI4NDZ8&ixlib=rb-4.0.3&q=80&w=1080"
    },
    "7": {
        "productID": "7",
        "productName": "Watch",
        "productBrand": "Rolex",
        "Category": "Accessories",
        "Price (INR)": 350000,
        "Product Description": "Luxury timepiece crafted with precision, elegance, and durability.",
        "Product Image": "https://images.unsplash.com/photo-1495857000853-fe46c8aefc30?crop=entropy&cs=tinysrgb&fit=max&fm=jpg&ixid=M3w1NjQ3NjZ8MHwxfHJhbmRvbXx8fHx8fHx8fDE3MDc2NTI4NDd8&ixlib=rb-4.0.3&q=80&w=1080"
    },
    "8": {
        "productID": "8",
        "productName": "Backpack",
        "productBrand": "North Face",
        "Category": "Accessories",
        "Price (INR)": 7000,
        "Product Description": "Durable backpack with ample storage space and comfortable shoulder straps.",
        "Product Image": "https://images.unsplash.com/photo-1529018576489-4d1b669bdb15?crop=entropy&cs=tinysrgb&fit=max&fm=jpg&ixid=M3w1NjQ3NjZ8MHwxfHJhbmRvbXx8fHx8fHx8fDE3MDc2NTI4NDh8&ixlib=rb-4.0.3&q=80&w=1080"
    },
    "9": {
        "productID": "9",
        "productName": "Sunglasses",
        "productBrand": "Ray-Ban",
        "Category": "Accessories",
        "Price (INR)": 10500,
        "Product Description": "Classic aviator sunglasses with polarized lenses for superior sun protection.",
        "Product Image": "https://images.unsplash.com/photo-1622019450027-a7a0f7311122?crop=entropy&cs=tinysrgb&fit=max&fm=jpg&ixid=M3w1NjQ3NjZ8MHwxfHJhbmRvbXx8fHx8fHx8fDE3MDc2NTI4NDl8&ixlib=rb-4.0.3&q=80&w=1080"
    },
    "10": {
        "productID": "10",
        "productName": "Tablet",
        "productBrand": "Apple",
        "Category": "Electronics",
        "Price (INR)": 42000,
        "Product Description": "iPad with stunning retina display, powerful A12 Bionic chip, and all-day battery life.",
        "Product Image": "https://images.unsplash.com/photo-1520607162513-77705c0f0d4a?crop=entropy&cs=tinysrgb&fit=max&fm=jpg&ixid=M3w1NjQ3NjZ8MHwxfHJhbmRvbXx8fHx8fHx8fDE3MDc2NTI4NTB8&ixlib=rb-4.0.3&q=80&w=1080"
    },
    "11": {
        "productID": "11",
        "productName": "TV",
        "productBrand": "LG",
        "Category": "Electronics",
        "Price (INR)": 84000,
        "Product Description": "Smart TV with immersive picture quality, built-in AI, and webOS for seamless streaming.",
        "Product Image": "https://images.unsplash.com/photo-1587892106866-e6b362b35449?crop=entropy&cs=tinysrgb&fit=max&fm=jpg&ixid=M3w1NjQ3NjZ8MHwxfHJhbmRvbXx8fHx8fHx8fDE3MDc2NTI4NTF8&ixlib=rb-4.0.3&q=80&w=1080"
    },
    "12": {
        "productID": "12",
        "productName": "Dress",
        "productBrand": "H&M",
        "Category": "Clothing",
        "Price (INR)": 2100,
        "Product Description": "Fashionable dress from H&M's latest collection, perfect for any occasion.",
        "Product Image": "https://images.unsplash.com/photo-1606996251752-b49b347c01b5?crop=entropy&cs=tinysrgb&fit=max&fm=jpg&ixid=M3w1NjQ3NjZ8MHwxfHJhbmRvbXx8fHx8fHx8fDE3MDc2NTI4NTJ8&ixlib=rb-4.0.3&q=80&w=1080"
    },
    "13": {
        "productID": "13",
        "productName": "Shorts",
        "productBrand": "Under Armour",
        "Category": "Clothing",
        "Price (INR)": 2800,
        "Product Description": "Athletic shorts with moisture-wicking technology, ensuring comfort during workouts.",
        "Product Image": "https://images.unsplash.com/photo-1575728472538-12f60bcb7a94?crop=entropy&cs=tinysrgb&fit=max&fm=jpg&ixid=M3w1NjQ3NjZ8MHwxfHJhbmRvbXx8fHx8fHx8fDE3MDc2NTI4NTJ8&ixlib=rb-4.0.3&q=80&w=1080"
    },
    "14": {
        "productID": "14",
        "productName": "Boots",
        "productBrand": "Timberland",
        "Category": "Clothing",
        "Price (INR)": 8400,
        "Product Description": "Premium leather boots with rugged durability and all-day comfort.",
        "Product Image": "https://images.unsplash.com/photo-1638247025967-b4e38f787b76?crop=entropy&cs=tinysrgb&fit=max&fm=jpg&ixid=M3w1NjQ3NjZ8MHwxfHJhbmRvbXx8fHx8fHx8fDE3MDc2NTI4NTN8&ixlib=rb-4.0.3&q=80&w=1080"
    },
    "15": {
        "productID": "15",
        "productName": "Bracelet",
        "productBrand": "Pandora",
        "Category": "Accessories",
        "Price (INR)": 5600,
        "Product Description": "Elegant bracelet adorned with sparkling charms, ideal for adding a touch of glamour to any outfit.",
        "Product Image": "https://images.unsplash.com/photo-1703034390375-952c3b191c6f?crop=entropy&cs=tinysrgb&fit=max&fm=jpg&ixid=M3w1NjQ3NjZ8MHwxfHJhbmRvbXx8fHx8fHx8fDE3MDc2NTI4NTR8&ixlib=rb-4.0.3&q=80&w=1080"
    },
    "16": {
        "productID": "16",
        "productName": "Wallet",
        "productBrand": "Gucci",
        "Category": "Accessories",
        "Price (INR)": 21000,
        "Product Description": "Luxury wallet crafted from fine leather, featuring iconic Gucci logo detail.",
        "Product Image": "https://images.unsplash.com/photo-1675668409093-244704d3ba93?crop=entropy&cs=tinysrgb&fit=max&fm=jpg&ixid=M3w1NjQ3NjZ8MHwxfHJhbmRvbXx8fHx8fHx8fDE3MDc2NTI4NTV8&ixlib=rb-4.0.3&q=80&w=1080"
    },
    "17": {
        "productID": "17",
        "productName": "Keyboard",
        "productBrand": "Logitech",
        "Category": "Electronics",
        "Price (INR)": 3500,
        "Product Description": "High-performance keyboard with customizable RGB lighting and mechanical switches.",
        "Product Image": "https://images.unsplash.com/photo-1617900879256-45020f3700ac?crop=entropy&cs=tinysrgb&fit=max&fm=jpg&ixid=M3w1NjQ3NjZ8MHwxfHJhbmRvbXx8fHx8fHx8fDE3MDc2NTI4NTZ8&ixlib=rb-4.0.3&q=80&w=1080"
    },
    "18": {
        "productID": "18",
        "productName": "Mouse",
        "productBrand": "Razer",
        "Category": "Electronics",
        "Price (INR)": 4900,
        "Product Description": "Gaming mouse with advanced optical sensor and ergonomic design for precision and comfort.",
        "Product Image": "https://images.unsplash.com/photo-1623998021930-8029ef1f382a?crop=entropy&cs=tinysrgb&fit=max&fm=jpg&ixid=M3w1NjQ3NjZ8MHwxfHJhbmRvbXx8fHx8fHx8fDE3MDc2NTI4NTZ8&ixlib=rb-4.0.3&q=80&w=1080"
    },
    "19": {
        "productID": "19",
        "productName": "Jacket",
        "productBrand": "Columbia",
        "Category": "Clothing",
        "Price (INR)": 7000,
        "Product Description": "Waterproof jacket with thermal reflective lining, perfect for outdoor adventures.",
        "Product Image": "https://images.unsplash.com/photo-1633965288984-f7928914395d?crop=entropy&cs=tinysrgb&fit=max&fm=jpg&ixid=M3w1NjQ3NjZ8MHwxfHJhbmRvbXx8fHx8fHx8fDE3MDc2NTI4NTd8&ixlib=rb-4.0.3&q=80&w=1080"
    },
    "20": {
        "productID": "20",
        "productName": "Scarf",
        "productBrand": "Burberry",
        "Category": "Clothing",
        "Price (INR)": 10500,
        "Product Description": "Luxurious cashmere scarf featuring Burberry's iconic check pattern.",
        "Product Image": "https://images.unsplash.com/photo-1542358203625-5622f8ca8282?crop=entropy&cs=tinysrgb&fit=max&fm=jpg&ixid=M3w1NjQ3NjZ8MHwxfHJhbmRvbXx8fHx8fHx8fDE3MDc2NTI4NTh8&ixlib=rb-4.0.3&q=80&w=1080"
    },
    "21": {
        "productID": "21",
        "productName": "Sandals",
        "productBrand": "Birkenstock",
        "Category": "Clothing",
        "Price (INR)": 4200,
        "Product Description": "Comfortable sandals with contoured footbed and adjustable straps for a customized fit.",
        "Product Image": "https://images.unsplash.com/photo-1693439445707-258c80d7320e?crop=entropy&cs=tinysrgb&fit=max&fm=jpg&ixid=M3w1NjQ3NjZ8MHwxfHJhbmRvbXx8fHx8fHx8fDE3MDc2NTI4NTl8&ixlib=rb-4.0.3&q=80&w=1080"
    },
    "22": {
        "productID": "22",
        "productName": "Ring",
        "productBrand": "Tiffany & Co.",
        "Category": "Accessories",
        "Price (INR)": 35000,
        "Product Description": "Exquisite ring crafted from sterling silver, adorned with Tiffany's signature elegance.",
        "Product Image": "https://images.unsplash.com/photo-1690655952950-6055971eea3e?crop=entropy&cs=tinysrgb&fit=max&fm=jpg&ixid=M3w1NjQ3NjZ8MHwxfHJhbmRvbXx8fHx8fHx8fDE3MDc2NTI4NTl8&ixlib=rb-4.0.3&q=80&w=1080"
    },
    "23": {
        "productID": "23",
        "productName": "External Hard Drive",
        "productBrand": "Western Digital",
        "Category": "Electronics",
        "Price (INR)": 5600,
        "Product Description": "High-capacity external hard drive for storing and backing up data with fast transfer speeds.",
        "Product Image": "https://images.unsplash.com/photo-1534026235567-6f7f77c79be4?crop=entropy&cs=tinysrgb&fit=max&fm=jpg&ixid=M3w1NjQ3NjZ8MHwxfHJhbmRvbXx8fHx8fHx8fDE3MDc2NTI4NjB8&ixlib=rb-4.0.3&q=80&w=1080"
    },
    "24": {
        "productID": "24",
        "productName": "Printer",
        "productBrand": "HP",
        "Category": "Electronics",
        "Price (INR)": 5600,
        "Product Description": "All-in-one printer with wireless connectivity and high-quality printing capabilities.",
        "Product Image": "https://images.unsplash.com/photo-1705475025559-ad8efdedc74f?crop=entropy&cs=tinysrgb&fit=max&fm=jpg&ixid=M3w1NjQ3NjZ8MHwxfHJhbmRvbXx8fHx8fHx8fDE3MDc2NTI4NjF8&ixlib=rb-4.0.3&q=80&w=1080"
    },
    "25": {
        "productID": "25",
        "productName": "Hoodie",
        "productBrand": "Champion",
        "Category": "Clothing",
        "Price (INR)": 10500,
        "Product Description": "Cozy hoodie with Champion's iconic logo, perfect for casual wear.",
        "Product Image": "https://images.unsplash.com/photo-1618333286955-6391a94f70fb?crop=entropy&cs=tinysrgb&fit=max&fm=jpg&ixid=M3w1NjQ3NjZ8MHwxfHJhbmRvbXx8fHx8fHx8fDE3MDc2NTI4NjJ8&ixlib=rb-4.0.3&q=80&w=1080"
    },
    "26": {
        "productID": "26",
        "productName": "Leggings",
        "productBrand": "Lululemon",
        "Category": "Clothing",
        "Price (INR)": 3150,
        "Product Description": "High-quality leggings designed for comfort and performance during workouts or everyday wear.",
        "Product Image": "https://images.unsplash.com/photo-1676317457455-feee9888872c?crop=entropy&cs=tinysrgb&fit=max&fm=jpg&ixid=M3w1NjQ3NjZ8MHwxfHJhbmRvbXx8fHx8fHx8fDE3MDc2NTI4NjN8&ixlib=rb-4.0.3&q=80&w=1080"
    },
    "27": {
        "productID": "27",
        "productName": "Heels",
        "productBrand": "Steve Madden",
        "Category": "Clothing",
        "Price (INR)": 5400,
        "Product Description": "Stylish heels with a modern design and cushioned insole for all-day comfort.",
        "Product Image": "https://images.unsplash.com/photo-1565325058701-b1cb0be324f3?crop=entropy&cs=tinysrgb&fit=max&fm=jpg&ixid=M3w1NjQ3NjZ8MHwxfHJhbmRvbXx8fHx8fHx8fDE3MDc2NTI4NjN8&ixlib=rb-4.0.3&q=80&w=1080"
    },
    "28": {
        "productID": "28",
        "productName": "Necklace",
        "productBrand": "Swarovski",
        "Category": "Accessories",
        "Price (INR)": 4900,
        "Product Description": "Sparkling necklace adorned with Swarovski crystals, adding a touch of elegance to any ensemble.",
        "Product Image": "https://images.unsplash.com/photo-1707222611620-41c17060c4de?crop=entropy&cs=tinysrgb&fit=max&fm=jpg&ixid=M3w1NjQ3NjZ8MHwxfHJhbmRvbXx8fHx8fHx8fDE3MDc2NTI4NjR8&ixlib=rb-4.0.3&q=80&w=1080"
    },
    "29": {
        "productID": "29",
        "productName": "Laptop Sleeve",
        "productBrand": "Case Logic",
        "Category": "Accessories",
        "Price (INR)": 14000,
        "Product Description": "Protective laptop sleeve with padded interior and slim design for easy portability.",
        "Product Image": "https://images.unsplash.com/photo-1498050108023-c5249f4df085?crop=entropy&cs=tinysrgb&fit=max&fm=jpg&ixid=M3w1NjQ3NjZ8MHwxfHJhbmRvbXx8fHx8fHx8fDE3MDc2NTI4NjV8&ixlib=rb-4.0.3&q=80&w=1080"
    },
    "30": {
        "productID": "30",
        "productName": "Smart Speaker",
        "productBrand": "Amazon",
        "Category": "Electronics",
        "Price (INR)": 1400,
        "Product Description": "Voice-controlled smart speaker with Alexa, delivering immersive sound and smart home capabilities.",
        "Product Image": "https://images.unsplash.com/photo-1512146431923-80b5cadeedc1?crop=entropy&cs=tinysrgb&fit=max&fm=jpg&ixid=M3w1NjQ3NjZ8MHwxfHJhbmRvbXx8fHx8fHx8fDE3MDc2NTI4NjZ8&ixlib=rb-4.0.3&q=80&w=1080"
    },
    "31": {
        "productID": "31",
        "productName": "Smartwatch",
        "productBrand": "Fitbit",
        "Category": "Electronics",
        "Price (INR)": 5600,
        "Product Description": "Fitness-oriented smartwatch with heart rate monitoring, activity tracking, and built-in GPS.",
        "Product Image": "https://images.unsplash.com/photo-1599468942589-169d67c8d30a?crop=entropy&cs=tinysrgb&fit=max&fm=jpg&ixid=M3w1NjQ3NjZ8MHwxfHJhbmRvbXx8fHx8fHx8fDE3MDc2NTI4Njd8&ixlib=rb-4.0.3&q=80&w=1080"
    },
    "32": {
        "productID": "32",
        "productName": "Polo Shirt",
        "productBrand": "Ralph Lauren",
        "Category": "Clothing",
        "Price (INR)": 10500,
        "Product Description": "Classic polo shirt crafted from soft cotton, featuring Ralph Lauren's signature pony logo.",
        "Product Image": "https://images.unsplash.com/photo-1471286174890-9c112ffca5b4?crop=entropy&cs=tinysrgb&fit=max&fm=jpg&ixid=M3w1NjQ3NjZ8MHwxfHJhbmRvbXx8fHx8fHx8fDE3MDc2NTI4Njh8&ixlib=rb-4.0.3&q=80&w=1080"
    },
    "33": {
        "productID": "33",
        "productName": "Skirt",
        "productBrand": "Zara",
        "Category": "Clothing",
        "Price (INR)": 3600,
        "Product Description": "Trendy skirt with a flattering silhouette, perfect for both casual and dressy occasions.",
        "Product Image": "https://images.unsplash.com/photo-1618143445386-80a867d64641?crop=entropy&cs=tinysrgb&fit=max&fm=jpg&ixid=M3w1NjQ3NjZ8MHwxfHJhbmRvbXx8fHx8fHx8fDE3MDc2NTI4Njl8&ixlib=rb-4.0.3&q=80&w=1080"
    },
    "34": {
        "productID": "34",
        "productName": "Loafers",
        "productBrand": "Clarks",
        "Category": "Clothing",
        "Price (INR)": 2450,
        "Product Description": "Stylish loafers crafted from premium leather, offering timeless style and all-day comfort.",
        "Product Image": "https://images.unsplash.com/photo-1517141544637-42b300cb4ee9?crop=entropy&cs=tinysrgb&fit=max&fm=jpg&ixid=M3w1NjQ3NjZ8MHwxfHJhbmRvbXx8fHx8fHx8fDE3MDc2NTI4NzB8&ixlib=rb-4.0.3&q=80&w=1080"
    },
    "35": {
        "productID": "35",
        "productName": "Belt",
        "productBrand": "Hermes",
        "Category": "Accessories",
        "Price (INR)": 7000,
        "Product Description": "Luxury leather belt with iconic Hermes buckle, adding sophistication to any outfit.",
        "Product Image": "https://images.unsplash.com/photo-1526755393771-bf2e591f33a0?crop=entropy&cs=tinysrgb&fit=max&fm=jpg&ixid=M3w1NjQ3NjZ8MHwxfHJhbmRvbXx8fHx8fHx8fDE3MDc2NTI4NzB8&ixlib=rb-4.0.3&q=80&w=1080"
    },
    "36": {
        "productID": "36",
        "productName": "Monitor",
        "productBrand": "Dell",
        "Category": "Electronics",
        "Price (INR)": 28000,
        "Product Description": "High-resolution monitor with vibrant colors and slim bezels, perfect for work or entertainment.",
        "Product Image": "https://images.unsplash.com/photo-1610389051254-64849803c8fd?crop=entropy&cs=tinysrgb&fit=max&fm=jpg&ixid=M3w1NjQ3NjZ8MHwxfHJhbmRvbXx8fHx8fHx8fDE3MDc2NTI4NzF8&ixlib=rb-4.0.3&q=80&w=1080"
    },
    "37": {
        "productID": "37",
        "productName": "Camera",
        "productBrand": "Canon",
        "Category": "Electronics",
        "Price (INR)": 21000,
        "Product Description": "DSLR camera with advanced autofocus system and high-quality image sensor for stunning photography.",
        "Product Image": "https://images.unsplash.com/photo-1623621461302-e6b5236629cb?crop=entropy&cs=tinysrgb&fit=max&fm=jpg&ixid=M3w1NjQ3NjZ8MHwxfHJhbmRvbXx8fHx8fHx8fDE3MDc2NTI4NzJ8&ixlib=rb-4.0.3&q=80&w=1080"
    },
    "38": {
        "productID": "38",
        "productName": "Sweater",
        "productBrand": "Gap",
        "Category": "Clothing",
        "Price (INR)": 35000,
        "Product Description": "Cozy sweater knitted from soft yarn, ideal for layering during colder weather.",
        "Product Image": "https://images.unsplash.com/photo-1675190558564-cc1ec83e9e0c?crop=entropy&cs=tinysrgb&fit=max&fm=jpg&ixid=M3w1NjQ3NjZ8MHwxfHJhbmRvbXx8fHx8fHx8fDE3MDc2NTI4NzN8&ixlib=rb-4.0.3&q=80&w=1080"
    },
    "39": {
        "productID": "39",
        "productName": "Leg Warmers",
        "productBrand": "American Apparel",
        "Category": "Clothing",
        "Price (INR)": 10500,
        "Product Description": "Stylish leg warmers made from stretchy fabric, adding a trendy touch to any outfit.",
        "Product Image": "https://images.unsplash.com/photo-1555836721-6fec17bd948a?crop=entropy&cs=tinysrgb&fit=max&fm=jpg&ixid=M3w1NjQ3NjZ8MHwxfHJhbmRvbXx8fHx8fHx8fDE3MDc2NTI4NzR8&ixlib=rb-4.0.3&q=80&w=1080"
    },
    "40": {
        "productID": "40",
        "productName": "Flip Flops",
        "productBrand": "Havaianas",
        "Category": "Clothing",
        "Price (INR)": 1050,
        "Product Description": "Comfortable flip flops with durable rubber sole, perfect for beach days or casual outings.",
        "Product Image": "https://images.unsplash.com/photo-1672668799590-19d593c68ec7?crop=entropy&cs=tinysrgb&fit=max&fm=jpg&ixid=M3w1NjQ3NjZ8MHwxfHJhbmRvbXx8fHx8fHx8fDE3MDc2NTI4NzR8&ixlib=rb-4.0.3&q=80&w=1080"
    },
    "41": {
        "productID": "41",
        "productName": "Earrings",
        "productBrand": "Pandora",
        "Category": "Accessories",
        "Price (INR)": 1400,
        "Product Description": "Elegant earrings adorned with sparkling stones, adding a touch of glamour to any look.",
        "Product Image": "https://images.unsplash.com/photo-1664925502795-83a700f7843c?crop=entropy&cs=tinysrgb&fit=max&fm=jpg&ixid=M3w1NjQ3NjZ8MHwxfHJhbmRvbXx8fHx8fHx8fDE3MDc2NTI4NzV8&ixlib=rb-4.0.3&q=80&w=1080"
    },
    "42": {
        "productID": "42",
        "productName": "Desk Lamp",
        "productBrand": "Ikea",
        "Category": "Electronics",
        "Price (INR)": 2800,
        "Product Description": "Modern desk lamp with adjustable brightness levels, perfect for work or study.",
        "Product Image": "https://images.unsplash.com/photo-1549833971-c4283bad0032?crop=entropy&cs=tinysrgb&fit=max&fm=jpg&ixid=M3w1NjQ3NjZ8MHwxfHJhbmRvbXx8fHx8fHx8fDE3MDc2NTI4NzZ8&ixlib=rb-4.0.3&q=80&w=1080"
    },
    "43": {
        "productID": "43",
        "productName": "Back Brace",
        "productBrand": "Mueller",
        "Category": "Accessories",
        "Price (INR)": 1400,
        "Product Description": "Supportive back brace for posture improvement and back pain relief.",
        "Product Image": "https://images.unsplash.com/photo-1559665181-0415962203c9?crop=entropy&cs=tinysrgb&fit=max&fm=jpg&ixid=M3w1NjQ3NjZ8MHwxfHJhbmRvbXx8fHx8fHx8fDE3MDc2NTI4Nzd8&ixlib=rb-4.0.3&q=80&w=1080"
    },
    "44": {
        "productID": "44",
        "productName": "Sun Hat",
        "productBrand": "Fila",
        "Category": "Clothing",
        "Price (INR)": 1400,
        "Product Description": "Stylish sun hat with wide brim for sun protection, perfect for outdoor activities.",
        "Product Image": "https://images.unsplash.com/photo-1501576003369-64f301d92efb?crop=entropy&cs=tinysrgb&fit=max&fm=jpg&ixid=M3w1NjQ3NjZ8MHwxfHJhbmRvbXx8fHx8fHx8fDE3MDc2NTI4Nzh8&ixlib=rb-4.0.3&q=80&w=1080"
    },
    "45": {
        "productID": "45",
        "productName": "Power Bank",
        "productBrand": "Anker",
        "Category": "Electronics",
        "Price (INR)": 2800,
        "Product Description": "High-capacity power bank for charging devices on the go, featuring fast charging technology.",
        "Product Image": "https://images.unsplash.com/photo-1669251921941-ae3645715017?crop=entropy&cs=tinysrgb&fit=max&fm=jpg&ixid=M3w1NjQ3NjZ8MHwxfHJhbmRvbXx8fHx8fHx8fDE3MDc2NTI4Nzh8&ixlib=rb-4.0.3&q=80&w=1080"
    }
}